ps2_analysis/__init__.py
ps2_analysis/data.py
ps2_analysis/enums.py
ps2_analysis/fire_groups/__init__.py
ps2_analysis/fire_groups/ammo.py
ps2_analysis/fire_groups/cone_of_fire.py
ps2_analysis/fire_groups/damage_profile.py
ps2_analysis/fire_groups/data_files.py
ps2_analysis/fire_groups/data_fixers.py
ps2_analysis/fire_groups/fire_group.py
ps2_analysis/fire_groups/fire_mode.py
ps2_analysis/fire_groups/fire_timing.py
ps2_analysis/fire_groups/generate.py
ps2_analysis/fire_groups/heat.py
ps2_analysis/fire_groups/joins.py
ps2_analysis/fire_groups/lock_on.py
ps2_analysis/fire_groups/projectile.py
ps2_analysis/fire_groups/queries.py
ps2_analysis/fire_groups/recoil.py
ps2_analysis/geometry_utils.py
ps2_analysis/utils.py
ps2_analysis/weapons/__init__.py
ps2_analysis/weapons/attachment.py
ps2_analysis/weapons/infantry/__init__.py
ps2_analysis/weapons/infantry/data_files.py
ps2_analysis/weapons/infantry/data_fixers.py
ps2_analysis/weapons/infantry/generate.py
ps2_analysis/weapons/infantry/infantry_weapon.py
ps2_analysis/weapons/joins.py
ps2_analysis/weapons/queries.py
ps2_analysis/weapons/vehicle/data_files.py
ps2_analysis/weapons/vehicle/data_fixers.py
ps2_analysis/weapons/vehicle/generate.py
ps2_analysis/weapons/vehicle/vehicle_weapon.py
ps2_analysis/weapons/weapon.py
ps2_analysis-0.28.0.dist-info/LICENSE
ps2_analysis-0.28.0.dist-info/WHEEL
ps2_analysis-0.28.0.dist-info/METADATA
ps2_analysis-0.28.0.dist-info/RECORD
