Metadata-Version: 2.1
Name: ps2-analysis
Version: 0.28.0
Summary: Daybreak Game's Planetside 2 data analysis (UNOFFICIAL)
Home-page: https://github.com/spascou/ps2-analysis
License: MIT
Author: Sylvain Pascou
Author-email: sylvain@pascou.net
Requires-Python: >=3.8,<4.0
Classifier: License :: OSI Approved :: MIT License
Classifier: Programming Language :: Python :: 3
Classifier: Programming Language :: Python :: 3.8
Requires-Dist: methodtools (>=0.4,<0.5)
Requires-Dist: ndjson (>=0.3,<0.4)
Requires-Dist: ps2-census (>=0.12,<0.13)
Requires-Dist: python-slugify (>=4.0,<5.0)
Requires-Dist: toml (>=0.9,<0.10)
Project-URL: Repository, https://github.com/spascou/ps2-analysis
